channelarchiver/__init__.py
channelarchiver/channelarchiver.py
channelarchiver/codes.py
channelarchiver/exceptions.py
channelarchiver/models.py
channelarchiver/structures.py
channelarchiver/utils.py
channelarchiver-1.0.0.dist-info/METADATA
channelarchiver-1.0.0.dist-info/RECORD
channelarchiver-1.0.0.dist-info/WHEEL
channelarchiver-1.0.0.dist-info/top_level.txt
