Metadata-Version: 2.1
Name: channelarchiver
Version: 1.0.0
Summary: Python client for the EPICS Channel Archiver.
Home-page: https://github.com/RobbieClarken/channelarchiver
Author: Robbie Clarken
Author-email: robbie.clarken@gmail.com
License: The MIT License (MIT)
Requires-Dist: tzlocal
